{
  "groups": [
    {
      "name": "chat",
      "type": "com.quick.member.common.config.params.ChatGptParamsConfig",
      "sourceType": "com.quick.member.common.config.params.ChatGptParamsConfig"
    },
    {
      "name": "midjourney",
      "type": "com.quick.member.common.config.params.MidjourneyParamsConfig",
      "sourceType": "com.quick.member.common.config.params.MidjourneyParamsConfig"
    },
    {
      "name": "service",
      "type": "com.quick.member.common.config.params.ServiceParamsConfig",
      "sourceType": "com.quick.member.common.config.params.ServiceParamsConfig"
    },
    {
      "name": "sms",
      "type": "com.quick.member.common.config.params.AuthSmsParamsConfig",
      "sourceType": "com.quick.member.common.config.params.AuthSmsParamsConfig"
    },
    {
      "name": "spring.datasource.member",
      "type": "javax.sql.DataSource",
      "sourceType": "com.quick.member.common.config.system.DataSourceConfig",
      "sourceMethod": "memberDataSource()"
    },
    {
      "name": "wechat",
      "type": "com.quick.member.common.config.params.WechatPayParamsConfig",
      "sourceType": "com.quick.member.common.config.params.WechatPayParamsConfig"
    }
  ],
  "properties": [
    {
      "name": "chat.api-key",
      "type": "java.lang.String",
      "sourceType": "com.quick.member.common.config.params.ChatGptParamsConfig"
    },
    {
      "name": "chat.host",
      "type": "java.lang.String",
      "sourceType": "com.quick.member.common.config.params.ChatGptParamsConfig"
    },
    {
      "name": "chat.port",
      "type": "java.lang.Integer",
      "sourceType": "com.quick.member.common.config.params.ChatGptParamsConfig"
    },
    {
      "name": "chat.tokens",
      "type": "java.lang.Integer",
      "sourceType": "com.quick.member.common.config.params.ChatGptParamsConfig"
    },
    {
      "name": "chat.tryleap-host",
      "type": "java.lang.String",
      "sourceType": "com.quick.member.common.config.params.ChatGptParamsConfig"
    },
    {
      "name": "chat.tryleap-key",
      "type": "java.lang.String",
      "sourceType": "com.quick.member.common.config.params.ChatGptParamsConfig"
    },
    {
      "name": "chat.tryleap-models",
      "type": "java.lang.String",
      "sourceType": "com.quick.member.common.config.params.ChatGptParamsConfig"
    },
    {
      "name": "chat.tryleap-path",
      "type": "java.lang.String",
      "sourceType": "com.quick.member.common.config.params.ChatGptParamsConfig"
    },
    {
      "name": "midjourney.application-id",
      "type": "java.lang.String",
      "description": "应用id",
      "sourceType": "com.quick.member.common.config.params.MidjourneyParamsConfig"
    },
    {
      "name": "midjourney.channel-id",
      "type": "java.lang.String",
      "description": "频道id",
      "sourceType": "com.quick.member.common.config.params.MidjourneyParamsConfig"
    },
    {
      "name": "midjourney.guild-id",
      "type": "java.lang.String",
      "description": "服务器id",
      "sourceType": "com.quick.member.common.config.params.MidjourneyParamsConfig"
    },
    {
      "name": "midjourney.session-id",
      "type": "java.lang.String",
      "description": "sessionid",
      "sourceType": "com.quick.member.common.config.params.MidjourneyParamsConfig"
    },
    {
      "name": "midjourney.token",
      "type": "java.lang.String",
      "description": "登入凭证",
      "sourceType": "com.quick.member.common.config.params.MidjourneyParamsConfig"
    },
    {
      "name": "service.attendance-count",
      "type": "java.lang.Long",
      "description": "签到奖励次数",
      "sourceType": "com.quick.member.common.config.params.ServiceParamsConfig"
    },
    {
      "name": "service.init-fee",
      "type": "java.math.BigDecimal",
      "description": "注册初始化费用(元)",
      "sourceType": "com.quick.member.common.config.params.ServiceParamsConfig"
    },
    {
      "name": "service.init-use-count",
      "type": "java.lang.Long",
      "description": "注册初始化次数(次)",
      "sourceType": "com.quick.member.common.config.params.ServiceParamsConfig"
    },
    {
      "name": "service.invit-fee",
      "type": "java.math.BigDecimal",
      "description": "邀请奖励费用(元)",
      "sourceType": "com.quick.member.common.config.params.ServiceParamsConfig"
    },
    {
      "name": "service.invit-length",
      "type": "java.lang.Integer",
      "description": "邀请码长度",
      "sourceType": "com.quick.member.common.config.params.ServiceParamsConfig"
    },
    {
      "name": "service.invit-use-count",
      "type": "java.lang.Long",
      "description": "邀请奖励次数(次)",
      "sourceType": "com.quick.member.common.config.params.ServiceParamsConfig"
    },
    {
      "name": "service.load-topic-path",
      "type": "java.lang.String",
      "description": "加载主题数据文件路径",
      "sourceType": "com.quick.member.common.config.params.ServiceParamsConfig"
    },
    {
      "name": "service.login-lock-time",
      "type": "java.lang.Long",
      "description": "登入超时时间(分)",
      "sourceType": "com.quick.member.common.config.params.ServiceParamsConfig"
    },
    {
      "name": "service.member-use-count",
      "type": "java.lang.Long",
      "description": "会员每日使用次数上限",
      "sourceType": "com.quick.member.common.config.params.ServiceParamsConfig"
    },
    {
      "name": "service.minio-base-url",
      "type": "java.lang.String",
      "description": "minio baseUrl",
      "sourceType": "com.quick.member.common.config.params.ServiceParamsConfig"
    },
    {
      "name": "service.order-time-out",
      "type": "java.lang.Long",
      "description": "订单超时时间(分钟)",
      "sourceType": "com.quick.member.common.config.params.ServiceParamsConfig"
    },
    {
      "name": "sms.access-key-id",
      "type": "java.lang.String",
      "description": "accessKeyId",
      "sourceType": "com.quick.member.common.config.params.AuthSmsParamsConfig"
    },
    {
      "name": "sms.access-key-secret",
      "type": "java.lang.String",
      "description": "accessKeySecret",
      "sourceType": "com.quick.member.common.config.params.AuthSmsParamsConfig"
    },
    {
      "name": "sms.app-code",
      "type": "java.lang.String",
      "description": "阿里巴巴订购的短信产品appCode",
      "sourceType": "com.quick.member.common.config.params.AuthSmsParamsConfig"
    },
    {
      "name": "sms.host",
      "type": "java.lang.String",
      "description": "短信发送验证码host",
      "sourceType": "com.quick.member.common.config.params.AuthSmsParamsConfig"
    },
    {
      "name": "sms.length",
      "type": "java.lang.String",
      "description": "短信验证码长度",
      "sourceType": "com.quick.member.common.config.params.AuthSmsParamsConfig"
    },
    {
      "name": "sms.minute",
      "type": "java.lang.String",
      "description": "短信有效时间(秒)",
      "sourceType": "com.quick.member.common.config.params.AuthSmsParamsConfig"
    },
    {
      "name": "sms.path",
      "type": "java.lang.String",
      "description": "发送验证路径",
      "sourceType": "com.quick.member.common.config.params.AuthSmsParamsConfig"
    },
    {
      "name": "sms.security-token",
      "type": "java.lang.String",
      "description": "securityToken",
      "sourceType": "com.quick.member.common.config.params.AuthSmsParamsConfig"
    },
    {
      "name": "sms.sms-sign-id",
      "type": "java.lang.String",
      "description": "短信前缀ID（签名ID）",
      "sourceType": "com.quick.member.common.config.params.AuthSmsParamsConfig"
    },
    {
      "name": "sms.template-id",
      "type": "java.lang.String",
      "description": "短信正文ID（模板ID）",
      "sourceType": "com.quick.member.common.config.params.AuthSmsParamsConfig"
    },
    {
      "name": "wechat.api-v3-key",
      "type": "java.lang.String",
      "description": "APIv3密钥(在微信支付回调通知和商户获取平台证书使用APIv3密钥)",
      "sourceType": "com.quick.member.common.config.params.WechatPayParamsConfig"
    },
    {
      "name": "wechat.app-id",
      "type": "java.lang.String",
      "description": "公众号appid(和商户id绑定过)",
      "sourceType": "com.quick.member.common.config.params.WechatPayParamsConfig"
    },
    {
      "name": "wechat.key-path",
      "type": "java.lang.String",
      "description": "必填：apiclient_cert.p12证书文件的绝对路径，或者以classpath:开头的类路径。",
      "sourceType": "com.quick.member.common.config.params.WechatPayParamsConfig"
    },
    {
      "name": "wechat.mch-key",
      "type": "java.lang.String",
      "description": "必填：APIv2密钥（调用v2版本的API时，需用APIv2密钥生成签名）",
      "sourceType": "com.quick.member.common.config.params.WechatPayParamsConfig"
    },
    {
      "name": "wechat.merchant-id",
      "type": "java.lang.String",
      "description": "商户id",
      "sourceType": "com.quick.member.common.config.params.WechatPayParamsConfig"
    },
    {
      "name": "wechat.notify-domain",
      "type": "java.lang.String",
      "description": "接收结果通知地址",
      "sourceType": "com.quick.member.common.config.params.WechatPayParamsConfig"
    },
    {
      "name": "wechat.private-cert-path",
      "type": "java.lang.String",
      "description": "必填：apiclient_cert.pem证书文件的绝对路径，或者以classpath:开头的类路径。",
      "sourceType": "com.quick.member.common.config.params.WechatPayParamsConfig"
    },
    {
      "name": "wechat.private-key",
      "type": "java.lang.String",
      "description": "商户私钥",
      "sourceType": "com.quick.member.common.config.params.WechatPayParamsConfig"
    },
    {
      "name": "wechat.private-key-path",
      "type": "java.lang.String",
      "description": "必填：apiclient_key.pem证书文件的绝对路径，或者以classpath:开头的类路径。",
      "sourceType": "com.quick.member.common.config.params.WechatPayParamsConfig"
    }
  ],
  "hints": []
}